np3-0.2.dist-info/RECORD
np3-0.2.dist-info/LICENSE
np3-0.2.dist-info/WHEEL
np3-0.2.dist-info/top_level.txt
np3-0.2.dist-info/METADATA
np3/_native.cpython-310-x86_64-linux-gnu.so
np3/py.typed
np3/_native.pyi
np3/__init__.py
