Metadata-Version: 2.1
Name: np3
Version: 0.2
Summary: Fast library to load MP3 into NumPY arrays
License: Mozilla Public License Version 2.0
Project-URL: Homepage, https://gitlab.com/nARNcheg/np3
Classifier: Topic :: Multimedia :: Sound/Audio
Classifier: License :: OSI Approved :: Mozilla Public License 2.0 (MPL 2.0)
Classifier: Typing :: Typed
Requires-Python: >=3.10
License-File: LICENSE
Requires-Dist: numpy (>=1.7)
